skedaddle/__init__.py
skedaddle/data.py
skedaddle-0.0.2.dist-info/METADATA
skedaddle-0.0.2.dist-info/WHEEL
skedaddle-0.0.2.dist-info/RECORD
