Metadata-Version: 2.4
Name: skedaddle
Version: 0.0.2
Summary: Essential numerical computing extensions.
Author-email: Skedaddle <you@example.com>
Requires-Python: >=3.7
